insight/__init__.py
insight/analyzer.py
insight/cli.py
insight/detector.py
insight/reporter.py
insight/utils.py
insight_cli_sarang-0.2.5.dist-info/licenses/LICENSE
insight_cli_sarang-0.2.5.dist-info/METADATA
insight_cli_sarang-0.2.5.dist-info/WHEEL
insight_cli_sarang-0.2.5.dist-info/top_level.txt
insight_cli_sarang-0.2.5.dist-info/RECORD
