Metadata-Version: 2.4
Name: insight-cli-sarang
Version: 0.2.5
Summary: Insight is a Python-based CLI tool that analyzes codebases and generates detailed reports.
Home-page: https://github.com/ExplainHub/Insight-Py
Author: Arpit Sarang
Author-email: arpitsarang2020@gmail.com
Project-URL: Homepage, https://github.com/ExplainHub/Insight
Requires-Python: >=3.7
License-File: LICENSE
Dynamic: author-email
Dynamic: home-page
Dynamic: license-file
Dynamic: requires-python
